{
  "posts": [
    { "id": 1, "title": "Post 1" },
    { "id": 2, "title": "Post 2" },
    { "id": 3, "title": "Post 3" }
  ],
  "comments": [
    { "id": 1, "body": "some comment", "postId": 1 },
    { "id": 2, "body": "some comment", "postId": 1 }
  ],
  "books": [
  {
    "id": "b85e6983-d0a1-4c2c-ab59-f8f6c459fbbe",
    "author": "Brewer Herman",
    "bookTitle": "aute fugiat minim"
  },
  {
    "id": "f2cfe34f-4d16-4f28-a2f7-d52d04ba13f9",
    "author": "Aimee Morin",
    "bookTitle": "reprehenderit anim exercitation"
  },
  {
    "id": "4d8b5091-3eab-40e3-a5c2-44f7e7286528",
    "author": "Mccoy Mann",
    "bookTitle": "incididunt aliqua laboris"
  },
  {
    "id": "f554c7bc-9dac-435f-91d3-255c735ddf5e",
    "author": "Gilliam Goodman",
    "bookTitle": "irure cillum consectetur"
  },
  {
    "id": "60370b2f-2ca9-40e2-b1b1-b925c65015d7",
    "author": "Bentley Coleman",
    "bookTitle": "eiusmod nulla laboris"
  },
  {
    "id": "87bb9362-2bfb-4486-b3de-995a4cfd0e6f",
    "author": "Luann Kelly",
    "bookTitle": "ad sint proident"
  },
  {
    "id": "f2154fe4-aa9b-4c84-928c-89bd9595d60d",
    "author": "Vickie Parks",
    "bookTitle": "esse eiusmod ea"
  },
  {
    "id": "b290c085-afd2-4d42-a892-235fd56762fb",
    "author": "Katrina Farley",
    "bookTitle": "dolor irure ullamco"
  },
  {
    "id": "925778a6-0bbc-4b11-80b6-83c6d89748fe",
    "author": "Queen Malone",
    "bookTitle": "occaecat id mollit"
  },
  {
    "id": "0535950c-c99f-4002-8bbd-65274e18033a",
    "author": "Weiss Glenn",
    "bookTitle": "nostrud est ipsum"
  },
  {
    "id": "ef3c0d5a-9bc4-453b-b9f2-468714cabbda",
    "author": "Mcdowell Spence",
    "bookTitle": "consectetur incididunt cupidatat"
  },
  {
    "id": "454399d8-7310-4678-8425-e19c36b8a9f0",
    "author": "Wade Nash",
    "bookTitle": "non officia minim"
  },
  {
    "id": "2078d91b-5136-489a-adf3-82e1826e0042",
    "author": "Jackie Berry",
    "bookTitle": "culpa exercitation minim"
  },
  {
    "id": "81f11709-94bc-47a2-ae3e-26230f92b25b",
    "author": "Lizzie Morrison",
    "bookTitle": "adipisicing duis voluptate"
  },
  {
    "id": "afb42eae-a342-4b6c-975e-c95dbd8891a4",
    "author": "Knight Allen",
    "bookTitle": "nisi in mollit"
  },
  {
    "id": "0a1747d2-0e3e-4567-baec-5584968da47a",
    "author": "Carmela William",
    "bookTitle": "incididunt aute commodo"
  },
  {
    "id": "449c12ba-b76a-470d-8168-63833b3702c5",
    "author": "Nguyen Rhodes",
    "bookTitle": "elit velit duis"
  },
  {
    "id": "c1742921-4b64-4d3b-a4b7-b8dfa92c95c4",
    "author": "Snow Guerra",
    "bookTitle": "labore tempor reprehenderit"
  },
  {
    "id": "7a5a5a38-5394-4f1f-8f18-fae9ea46e418",
    "author": "Henderson Cole",
    "bookTitle": "incididunt sint proident"
  },
  {
    "id": "513855dc-94f6-4161-b2f7-7660b2605488",
    "author": "Madelyn Trevino",
    "bookTitle": "excepteur amet nulla"
  },
  {
    "id": "8bd93f33-95a4-4be7-aa91-44a7ff94b393",
    "author": "Tate Wilder",
    "bookTitle": "velit consequat cupidatat"
  },
  {
    "id": "6d63c995-7df6-4caa-9b49-988c8c019f5d",
    "author": "Hopper Rivers",
    "bookTitle": "in nisi velit"
  },
  {
    "id": "7ff6da2f-8973-4b2c-a727-337a0455f7c3",
    "author": "Tiffany Shannon",
    "bookTitle": "laborum duis sit"
  }
]
}
